include/sarase.h
sarase/__init__.py
src/add.cpp
src/module.cpp
_sarase.cpython-39-x86_64-linux-gnu.so
sarase-0.1.7.dist-info/LICENSE
sarase-0.1.7.dist-info/WHEEL
sarase-0.1.7.dist-info/METADATA
sarase-0.1.7.dist-info/RECORD
